testmon_dev/__init__.py
testmon_dev/common.py
testmon_dev/configure.py
testmon_dev/db.py
testmon_dev/process_code.py
testmon_dev/pytest_testmon.py
testmon_dev/testmon_core.py
testmon_dev/tmnetc.py
tmserver/__init__.py
tmserver/database.py
tmserver/wiring.py
pytest_testmon_dev-2.0.3.dist-info/LICENSE
pytest_testmon_dev-2.0.3.dist-info/METADATA
pytest_testmon_dev-2.0.3.dist-info/WHEEL
pytest_testmon_dev-2.0.3.dist-info/entry_points.txt
pytest_testmon_dev-2.0.3.dist-info/top_level.txt
pytest_testmon_dev-2.0.3.dist-info/RECORD
