Metadata-Version: 2.1
Name: pytest-testmon-dev
Version: 2.0.3
Summary: selects tests affected by changed files and methods
Author-email: Tibor Arpas <tibor@testmon.org>
License: AGPL
Keywords: testing,pytest,plugin
Classifier: Development Status :: 4 - Beta
Classifier: Intended Audience :: Developers
Classifier: Operating System :: POSIX
Classifier: Operating System :: Microsoft :: Windows
Classifier: Operating System :: MacOS :: MacOS X
Classifier: Topic :: Software Development :: Testing
Classifier: Topic :: Software Development :: Libraries
Classifier: Topic :: Utilities
Classifier: Programming Language :: Python
Classifier: Programming Language :: Python :: 3.7
Classifier: Programming Language :: Python :: 3.8
Classifier: Programming Language :: Python :: 3.9
Classifier: Programming Language :: Python :: 3.10
Classifier: Programming Language :: Python :: 3.11
Classifier: Programming Language :: Python :: 3 :: Only
Classifier: Framework :: Pytest
Requires-Python: >=3.7
License-File: LICENSE
Requires-Dist: pytest (<8,>=5)
Requires-Dist: coverage (<8,>=6)
Requires-Dist: boto3 (>=1.20.54)
Requires-Dist: gunicorn
